README.md
pyproject.toml
setup.py
erag/__init__.py
erag/eval.py
erag.egg-info/PKG-INFO
erag.egg-info/SOURCES.txt
erag.egg-info/dependency_links.txt
erag.egg-info/requires.txt
erag.egg-info/top_level.txt
erag/utils/__init__.py
erag/utils/utils.py