Metadata-Version: 2.1
Name: erag
Version: 0.0.1
Summary: the implementation of the eRAG score.
Home-page: https://github.com/alirezasalemi7/eRAG
Author: Alireza Salemi
Author-email: asalemi@cs.umass.edu
License: UNKNOWN
Platform: UNKNOWN
